flaskavel/__init__.py
flaskavel/cli_manager.py
flaskavel/framework.py
flaskavel/lab/__init__.py
flaskavel/lab/app.py
flaskavel/lab/alchemist/__init__.py
flaskavel/lab/alchemist/http/__init__.py
flaskavel/lab/alchemist/http/base_controller.py
flaskavel/lab/alchemist/http/base_form_request.py
flaskavel/lab/alchemist/http/base_middleware.py
flaskavel/lab/atomic/__init__.py
flaskavel/lab/atomic/environment.py
flaskavel/lab/beaker/__init__.py
flaskavel/lab/beaker/console/__init__.py
flaskavel/lab/beaker/console/command.py
flaskavel/lab/beaker/console/helpers.py
flaskavel/lab/beaker/console/output.py
flaskavel/lab/beaker/console/progress_bar.py
flaskavel/lab/beaker/console/reactor.py
flaskavel/lab/beaker/console/register.py
flaskavel/lab/beaker/console/commands/__init__.py
flaskavel/lab/beaker/console/commands/cache_clear.py
flaskavel/lab/beaker/console/commands/key_generate.py
flaskavel/lab/beaker/console/commands/loops_run.py
flaskavel/lab/beaker/console/commands/make_command.py
flaskavel/lab/beaker/console/commands/make_controller.py
flaskavel/lab/beaker/console/commands/make_middleware.py
flaskavel/lab/beaker/console/commands/schedule_work.py
flaskavel/lab/beaker/console/commands/serve.py
flaskavel/lab/beaker/console/stub/Command.stub
flaskavel/lab/beaker/console/stub/Controller.stub
flaskavel/lab/beaker/console/stub/Middleware.stub
flaskavel/lab/beaker/console/stub/__init__.py
flaskavel/lab/beaker/iterations/__init__.py
flaskavel/lab/beaker/iterations/loops.py
flaskavel/lab/beaker/paths/__init__.py
flaskavel/lab/beaker/paths/helpers.py
flaskavel/lab/beaker/routes/__init__.py
flaskavel/lab/beaker/routes/router.py
flaskavel/lab/beaker/scheduling/__init__.py
flaskavel/lab/beaker/scheduling/schedule.py
flaskavel/lab/catalyst/__init__.py
flaskavel/lab/catalyst/bootstrap_cache.py
flaskavel/lab/catalyst/colors.py
flaskavel/lab/catalyst/config.py
flaskavel/lab/catalyst/encryption.py
flaskavel/lab/catalyst/environment.py
flaskavel/lab/catalyst/exceptions.py
flaskavel-1.45.0.dist-info/LICENCE
flaskavel-1.45.0.dist-info/METADATA
flaskavel-1.45.0.dist-info/WHEEL
flaskavel-1.45.0.dist-info/entry_points.txt
flaskavel-1.45.0.dist-info/top_level.txt
flaskavel-1.45.0.dist-info/RECORD
