Metadata-Version: 2.1
Name: flaskavel
Version: 1.45.0
Summary: Your Laboratory for Elegant Web Development
Home-page: https://github.com/flaskavel/framework
Author: Raul Mauricio Uñate Castro
Author-email: raulmauriciounate@gmail.com
Classifier: Programming Language :: Python :: 3
Classifier: License :: OSI Approved :: MIT License
Classifier: Operating System :: OS Independent
Requires-Python: >=3.12
License-File: LICENCE
Requires-Dist: apscheduler>=3.11.0
Requires-Dist: bcrypt>=4.2.0
Requires-Dist: greenlet>=3.1.0
Requires-Dist: pyclean>=3.0.0
Requires-Dist: schedule>=1.2.2
Requires-Dist: SQLAlchemy>=2.0.35
Requires-Dist: typing-extensions>=4.12.2
Requires-Dist: python-dotenv>=1.0.1
Requires-Dist: cryptography>=43.0.3
Requires-Dist: Flask>=3.0.3
Requires-Dist: Flask-Cors>=5.0.0
